Metadata-Version: 2.1
Name: npu
Version: 0.3.900
Summary: Python client for using npu api
Home-page: https://getneuro.ai
Author: Neuro
Author-email: api@neuro-ai.co.uk
License: UNKNOWN
Platform: UNKNOWN
Classifier: Programming Language :: Python :: 3
Classifier: License :: OSI Approved :: MIT License
Classifier: Operating System :: OS Independent
Requires-Python: >=3.6
License-File: LICENSE
Requires-Dist: requests (>=2)
Requires-Dist: numpy (>=1.18)
Requires-Dist: dill
Requires-Dist: bson
Requires-Dist: tqdm
Requires-Dist: requests-toolbelt
Requires-Dist: cryptography (>=3.4.7)
